README.md
setup.py
single_factor_analysis/__init__.py
single_factor_analysis/factor_analysis.py
single_factor_analysis/test_factor_analysis.py
single_factor_analysis.egg-info/PKG-INFO
single_factor_analysis.egg-info/SOURCES.txt
single_factor_analysis.egg-info/dependency_links.txt
single_factor_analysis.egg-info/not-zip-safe
single_factor_analysis.egg-info/requires.txt
single_factor_analysis.egg-info/top_level.txt