Metadata-Version: 1.0
Name: single-factor-analysis
Version: 0.2.1
Summary: Python implementation of factor analysis
Home-page: http://github.com/kdmarrett/single_factor_analysis
Author: Karl Marrett
Author-email: kdmarrett@gmail.com
License: MIT
Platform: UNKNOWN
